tacks/__init__.py
tacks-0.0.0.dist-info/LICENSE
tacks-0.0.0.dist-info/METADATA
tacks-0.0.0.dist-info/WHEEL
tacks-0.0.0.dist-info/top_level.txt
tacks-0.0.0.dist-info/RECORD
