Metadata-Version: 2.1
Name: tacks
Version: 0.0.0
Summary: Pin requirements for Python apps
Home-page: https://github.com/bulatb/tacks
Author: Bulat Bochkariov
Author-email: pypi@bulat.bochkariov.com
License: UNKNOWN
Project-URL: Source, https://github.com/bulatb/tacks
Project-URL: Issues, https://github.com/bulatb/tacks/issues
Keywords: pin requirement dependency version pip-tools pip
Platform: UNKNOWN
Classifier: Programming Language :: Python :: 3 :: Only
Classifier: Programming Language :: Python :: 3.6
Classifier: Programming Language :: Python :: 3.7
Classifier: Programming Language :: Python :: 3.8
Classifier: Development Status :: 1 - Planning
Classifier: License :: OSI Approved :: MIT License
Classifier: Operating System :: OS Independent
Classifier: Intended Audience :: Developers
Classifier: Topic :: Software Development :: Libraries
Requires-Python: >=3.6
Provides-Extra: develop
Provides-Extra: test
